ament_package/__init__.py
ament_package/templates.py
ament_package/template/__init__.py
ament_package/template/environment_hook/__init__.py
ament_package/template/environment_hook/ament_prefix_path.bat
ament_package/template/environment_hook/ament_prefix_path.sh
ament_package/template/environment_hook/library_path.sh
ament_package/template/environment_hook/path.bat
ament_package/template/environment_hook/path.sh
ament_package/template/environment_hook/pkg_config_path.bat
ament_package/template/environment_hook/pkg_config_path.sh
ament_package/template/environment_hook/pythonpath.bat.in
ament_package/template/environment_hook/pythonpath.sh.in
ament_package/template/package_level/__init__.py
ament_package/template/package_level/local_setup.bash.in
ament_package/template/package_level/local_setup.bat.in
ament_package/template/package_level/local_setup.sh.in
ament_package/template/package_level/local_setup.zsh.in
ament_package/template/prefix_level/__init__.py
ament_package/template/prefix_level/_local_setup_util.py
ament_package/template/prefix_level/local_setup.bash
ament_package/template/prefix_level/local_setup.bat.in
ament_package/template/prefix_level/local_setup.sh.in
ament_package/template/prefix_level/local_setup.zsh
ament_package/template/prefix_level/setup.bash
ament_package/template/prefix_level/setup.bat.in
ament_package/template/prefix_level/setup.sh.in
ament_package/template/prefix_level/setup.zsh
ros_ament_package-0.17.2.data/data/share/ament_index/resource_index/packages/ament_package
ros_ament_package-0.17.2.data/data/share/ament_package/package.xml
ros_ament_package-0.17.2.dist-info/licenses/LICENSE
ros_ament_package-0.17.2.dist-info/METADATA
ros_ament_package-0.17.2.dist-info/WHEEL
ros_ament_package-0.17.2.dist-info/top_level.txt
ros_ament_package-0.17.2.dist-info/zip-safe
ros_ament_package-0.17.2.dist-info/RECORD
