Metadata-Version: 2.4
Name: ros-ament-package
Version: 0.17.2
Summary: Ament is a build system for federated packages.
Home-page: https://github.com/ament/ament_package/wiki
Download-URL: https://github.com/ament/ament_package/releases
Author: Dirk Thomas
Author-email: dthomas@osrfoundation.org
Maintainer: Dharini Dutia
Maintainer-email: dharini@openrobotics.org
License: Apache License, Version 2.0
Keywords: ROS
Classifier: Intended Audience :: Developers
Classifier: License :: OSI Approved :: Apache Software License
Classifier: Programming Language :: Python
Classifier: Topic :: Software Development
License-File: LICENSE
Dynamic: author
Dynamic: author-email
Dynamic: classifier
Dynamic: description
Dynamic: download-url
Dynamic: home-page
Dynamic: keywords
Dynamic: license
Dynamic: license-file
Dynamic: maintainer
Dynamic: maintainer-email
Dynamic: summary
